arcade_customerio_track_api/__init__.py
arcade_customerio_track_api/moar/Customerio_Track.json
arcade_customerio_track_api/moar/openapi.json
arcade_customerio_track_api/tools/__init__.py
arcade_customerio_track_api/tools/request_body_schemas.py
arcade_customerio_track_api/wrapper_tools/AddDeviceToCustomerProfile.json
arcade_customerio_track_api/wrapper_tools/AddPeopleToSegment.json
arcade_customerio_track_api/wrapper_tools/BatchProcessRequests.json
arcade_customerio_track_api/wrapper_tools/DeleteCustomer.json
arcade_customerio_track_api/wrapper_tools/GetTrackApiRegion.json
arcade_customerio_track_api/wrapper_tools/GlobalUnsubscribeUser.json
arcade_customerio_track_api/wrapper_tools/ManageEntity.json
arcade_customerio_track_api/wrapper_tools/MergeCustomerProfiles.json
arcade_customerio_track_api/wrapper_tools/RemoveCustomerDevice.json
arcade_customerio_track_api/wrapper_tools/RemoveUserFromSegment.json
arcade_customerio_track_api/wrapper_tools/ReportCustomMetrics.json
arcade_customerio_track_api/wrapper_tools/SendCustomerEvent.json
arcade_customerio_track_api/wrapper_tools/SubmitFormResponse.json
arcade_customerio_track_api/wrapper_tools/SuppressCustomerProfile.json
arcade_customerio_track_api/wrapper_tools/TrackAnonymousEvent.json
arcade_customerio_track_api/wrapper_tools/UnsuppressCustomerProfile.json
arcade_customerio_track_api/wrapper_tools/UpdateOrAddPerson.json
arcade_customerio_track_api-1.0.0.dist-info/METADATA
arcade_customerio_track_api-1.0.0.dist-info/WHEEL
arcade_customerio_track_api-1.0.0.dist-info/entry_points.txt
arcade_customerio_track_api-1.0.0.dist-info/licenses/LICENSE
arcade_customerio_track_api-1.0.0.dist-info/RECORD
